toon_format/__init__.py
toon_format/__main__.py
toon_format/_literal_utils.py
toon_format/_parsing_utils.py
toon_format/_scanner.py
toon_format/_string_utils.py
toon_format/_validation.py
toon_format/cli.py
toon_format/constants.py
toon_format/decoder.py
toon_format/encoder.py
toon_format/encoders.py
toon_format/logging_config.py
toon_format/normalize.py
toon_format/primitives.py
toon_format/py.typed
toon_format/types.py
toon_format/utils.py
toon_format/writer.py
toon_format-0.9.0b1.dist-info/METADATA
toon_format-0.9.0b1.dist-info/WHEEL
toon_format-0.9.0b1.dist-info/entry_points.txt
toon_format-0.9.0b1.dist-info/licenses/LICENSE
toon_format-0.9.0b1.dist-info/RECORD
