Metadata-Version: 2.4
Name: toon_format
Version: 0.9.0b1
Summary: A compact, human-readable serialization format designed for passing structured data to Large Language Models with significantly reduced token usage
Project-URL: Homepage, https://github.com/toon-format/toon-python
Project-URL: Repository, https://github.com/toon-format/toon-python
Project-URL: Documentation, https://github.com/toon-format/spec
Project-URL: Bug Tracker, https://github.com/toon-format/toon-python/issues
Author-email: Johann Schopplich <hello@johannschopplich.com>
License: MIT
License-File: LICENSE
Keywords: data-format,llm,serialization,token-efficient,toon
Classifier: Development Status :: 4 - Beta
Classifier: Intended Audience :: Developers
Classifier: License :: OSI Approved :: MIT License
Classifier: Programming Language :: Python :: 3
Classifier: Programming Language :: Python :: 3.8
Classifier: Programming Language :: Python :: 3.9
Classifier: Programming Language :: Python :: 3.10
Classifier: Programming Language :: Python :: 3.11
Classifier: Programming Language :: Python :: 3.12
Classifier: Programming Language :: Python :: 3.13
Classifier: Programming Language :: Python :: 3.14
Classifier: Topic :: Software Development :: Libraries :: Python Modules
Requires-Python: >=3.8
Requires-Dist: typing-extensions>=4.0.0; python_version < '3.10'
